fastapi_routesmanager/__init__.py
fastapi_routesmanager/exceptions_logger.py
fastapi_routesmanager/headers_logger.py
fastapi_routesmanager/routes_manager.py
fastapi_routesmanager-0.0.3.dist-info/METADATA
fastapi_routesmanager-0.0.3.dist-info/WHEEL
fastapi_routesmanager-0.0.3.dist-info/top_level.txt
fastapi_routesmanager-0.0.3.dist-info/RECORD
