Metadata-Version: 2.1
Name: fastapi-routesmanager
Version: 0.0.3
Summary: Manipulate requests before FastAPI processes them, and responses once finished.
Author-email: SirPaulO <me@sirpauloliver.com>
License: MIT License
Project-URL: Homepage, https://github.com/SirPaulO/fastapi_routesmanager
Project-URL: Bug Tracker, https://github.com/SirPaulO/fastapi_routesmanager/issues
Project-URL: Repository, https://github.com/SirPaulO/fastapi_routesmanager.git
Keywords: fastapi,middleware,router,routes,request,response,api
Classifier: Programming Language :: Python :: 3
Classifier: License :: OSI Approved :: MIT License
Classifier: Operating System :: OS Independent
Requires-Python: >=3.7
Requires-Dist: fastapi >=0.95.2
